embedded_utils/__init__.py
embedded_utils/functions.py
embedded_utils/main.py
embedded_utils/microcontroladores.py
embedded_utils-0.1.0.dist-info/entry_points.txt
embedded_utils-0.1.0.dist-info/LICENSE
embedded_utils-0.1.0.dist-info/METADATA
embedded_utils-0.1.0.dist-info/WHEEL
embedded_utils-0.1.0.dist-info/RECORD
