Metadata-Version: 2.1
Name: embedded-utils
Version: 0.1.0
Summary: CLI Program for Embedded Programming Utils
Home-page: https://github.com/Guilhermwn/embedded-utils
License: MIT
Keywords: embedded,CLI,microcontrollers,mikroc,pic
Author: Guilhermwn
Author-email: limaoplaykglp@gmail.com
Requires-Python: >=3.9,<4.0
Classifier: License :: OSI Approved :: MIT License
Classifier: Natural Language :: English
Classifier: Natural Language :: Portuguese
Classifier: Natural Language :: Portuguese (Brazilian)
Classifier: Programming Language :: Python
Classifier: Programming Language :: Python :: 3
Classifier: Programming Language :: Python :: 3.9
Classifier: Programming Language :: Python :: 3.10
Classifier: Programming Language :: Python :: 3.11
Classifier: Programming Language :: Python :: 3.12
Classifier: Programming Language :: Python :: 3 :: Only
Classifier: Programming Language :: Python :: 3.8
Classifier: Topic :: Software Development :: Libraries :: Python Modules
Requires-Dist: click (==8.1.7)
Requires-Dist: colorama (==0.4.6)
Requires-Dist: lorem (==0.1.1)
Requires-Dist: markdown-it-py (==3.0.0)
Requires-Dist: mdurl (==0.1.2)
Requires-Dist: pygments (==2.18.0)
Requires-Dist: pyserial (==3.5)
Requires-Dist: rich (==13.7.1)
Requires-Dist: shellingham (==1.5.4)
Requires-Dist: tabulate (==0.9.0)
Requires-Dist: typer (==0.12.3)
Requires-Dist: typing-extensions (==4.12.0)
Project-URL: Repository, https://github.com/Guilhermwn/embedded-utils
